{
  "id": "live_doc_2ae5e680b05faa3b:000",
  "document_id": "live_doc_2ae5e680b05faa3b",
  "path": "04_MAIN_CHARACTER/README.md",
  "title": "04_MAIN_CHARACTER",
  "section": "04_MAIN_CHARACTER",
  "summary": "`04_MAIN_CHARACTER` is the live character surface.",
  "root": "04_MAIN_CHARACTER",
  "category": "04_MAIN_CHARACTER:README.md",
  "url": "https://crangprang.github.io/TRINITY_WIKI_AI_READER/ai/live/chunks/live_doc_2ae5e680b05faa3b_000.json",
  "text": "# 04_MAIN_CHARACTER\n\n`04_MAIN_CHARACTER` is the live character surface.",
  "metadata": {
    "char_count": 71,
    "sha256": "19e0a93f57e107055584123d7d97768541fa36ec88b4659b589a9234401345c0"
  }
}