{
  "id": "doc_2e542fd964d0a38a:004",
  "document_id": "doc_2e542fd964d0a38a",
  "path": "wiki/events/singularities/백해무익.md",
  "wiki_path": "events/singularities/백해무익.md",
  "title": "백해무익",
  "section": "붕괴 양상",
  "summary": "인내가 무너질 때 백색 제어가 붕괴하고, 하늘과 지상이 함께 추락하는 특이점.",
  "status": "draft",
  "type": "event",
  "tags": [
    "reader",
    "사건",
    "event"
  ],
  "updated": "2026-06-27",
  "url": "https://crangprang.github.io/TRINITY_WIKI_AI_READER/ai/chunks/doc_2e542fd964d0a38a_004.json",
  "text": "## 붕괴 양상\n\n백해무익의 붕괴 장면은 무지개색 번쩍임, 추락, 금지된 재난 통로, 에덴의 불시착으로 나타난다. 도시와 지형은 백색 제어가 풀리며 함께 무너지고, 천상으로 향하던 상승의 언어는 추락과 재결합의 압력으로 뒤집힌다.",
  "metadata": {
    "char_count": 128,
    "sha256": "0e61438e28ebcbbc406e8c61ef27093e4fcae3e8e3bb2a6cee273aa3f8a1fdb1"
  }
}