{
  "id": "doc_05eed2faa24f12f6:001",
  "document_id": "doc_05eed2faa24f12f6",
  "path": "wiki/universe/realms/balance/organizations/스트레인저.md",
  "wiki_path": "universe/realms/balance/organizations/스트레인저.md",
  "title": "스트레인저",
  "section": "개요",
  "summary": "스트레인저는 퍼시스 사건 이후 아홉 나라의 정주민 질서와 정교 체계 바깥으로 밀려난 사람들을 서로 잃어버리지 않게 붙드는 외지 공동체이자 정교가 배신자로 분류하는 이단 축이다.",
  "status": "draft",
  "type": "organization",
  "tags": [
    "universe",
    "balance",
    "organization",
    "heresy",
    "eremos"
  ],
  "updated": "2026-06-29",
  "url": "https://crangprang.github.io/TRINITY_WIKI_AI_READER/ai/chunks/doc_05eed2faa24f12f6_001.json",
  "text": "## 개요\n\n스트레인저는 아홉 나라의 정주민 질서와 정교 체계에서 이탈했거나 처음부터 편입되지 않은 사람들의 공동체 이름이다. 정교 기록은 이들을 배신자들의 이단 집단으로 분류하지만, 내부에서는 잠시 길 잃은 자들을 서로 잃어버리지 않게 붙드는 공동체로 자신들을 이해한다.\n\n스트레인저는 에레모스의 장막, 통과구, 지하 회랑, 야영지, 비공식 시장을 따라 움직인다. 구성원은 한곳에 오래 머무르지 않아도, 어느 길이 아직 살아 있고 어느 의뢰가 함정인지 공유한다.",
  "metadata": {
    "char_count": 259,
    "sha256": "a6b647ca9b5b3e800f4f4d5bc254d7db3a5d1ed7619e69ad8b7bc87dfc973490"
  }
}