{
  "id": "doc_ac7a1dc793b8b1d4:002",
  "document_id": "doc_ac7a1dc793b8b1d4",
  "path": "wiki/beings/creatures/알렉시아_원생_생물.md",
  "wiki_path": "beings/creatures/알렉시아_원생_생물.md",
  "title": "알렉시아 원생 생물",
  "section": "정체",
  "summary": "척삭군, 유리근막, 흑수해면이 지하 수분과 수정벽과 잉크 배수로 주변에서 이루는 알렉시아 미시 군체.",
  "status": "draft",
  "type": "being",
  "tags": [
    "reader",
    "존재",
    "being"
  ],
  "updated": "2026-06-26",
  "url": "https://crangprang.github.io/TRINITY_WIKI_AI_READER/ai/chunks/doc_ac7a1dc793b8b1d4_002.json",
  "text": "## 정체\n\n구성 생물은 다음과 같다.\n\n- 척삭군\n- 유리근막\n- 흑수해면",
  "metadata": {
    "char_count": 42,
    "sha256": "4a0f5bcf485870d4958a1666d6cff1bf3b19fea319c3afb9a34d7f8b229b59c8"
  }
}