{
  "id": "doc_8506b92a8e4c7b16:029",
  "document_id": "doc_8506b92a8e4c7b16",
  "path": "wiki/universe/realms/balance/nations/마사오트.md",
  "wiki_path": "universe/realms/balance/nations/마사오트.md",
  "title": "마사오트",
  "section": "날씨",
  "summary": "마사오트는 노틸러스호 본선을 중심으로 8척의 길드선이 도는 하늘 위 함대국가다. 본선 갑판의 풍차와 출항 준비, 구베르나의 탐험가 길드 본진, 우편 꾸러미와 비공정 함대가 이 나라의 좋은 말이며, 사람들은 땅보다 더 넓은 하늘길을 자기 국토처럼 여긴다.",
  "status": "draft",
  "type": "nation",
  "tags": [
    "reader",
    "국가",
    "nation"
  ],
  "updated": "2026-06-28",
  "url": "https://crangprang.github.io/TRINITY_WIKI_AI_READER/ai/chunks/doc_8506b92a8e4c7b16_029.json",
  "text": "### 날씨\n\n이 나라의 날씨는 티폰과의 거리다. 폭풍이 멀어지면 축제가 열리고, 가까워지면 적색 경보와 대피가 시작된다.",
  "metadata": {
    "char_count": 68,
    "sha256": "b59c61fb4fe12d7f62c0d1e35f2d7eacaa2d36934a281a3317eb6b54eda2f0fd"
  }
}