{
  "id": "doc_4c5c1b86d5d17b4a:002",
  "document_id": "doc_4c5c1b86d5d17b4a",
  "path": "wiki/universe/structure/삼위일체_우주.md",
  "wiki_path": "universe/structure/삼위일체_우주.md",
  "title": "삼위일체 우주",
  "section": "삼계의 상처와 꼬임",
  "summary": "창조계, 균형계, 파괴계가 서로 다른 위상에서 맞물리고 용기의문과 절제의문으로 직접 침투를 제한하는 우주.",
  "status": "draft",
  "type": "universe",
  "tags": [
    "universe",
    "structure",
    "삼위일체"
  ],
  "updated": "2026-06-30",
  "url": "https://crangprang.github.io/TRINITY_WIKI_AI_READER/ai/chunks/doc_4c5c1b86d5d17b4a_002.json",
  "text": "## 삼계의 상처와 꼬임\n\n삼계의 현재 형태는 완성 직전의 오리진에 남은 세 방향의 상처를 따라 굳은 결과다. 에마나치온과 칼시네이션은 세계를 단순히 새로 만들지 않았다. 그 사건들은 오리진에 형상화하려는 장력, 살아내려는 장력, 해체하려는 장력을 남겼고, 섭리는 그 상처를 완전히 지우는 대신 서로 분리된 세 세계의 틀로 봉합했다.\n\n형상화하려는 장력은 창조계로 굳었다. 이 장력은 세계를 설계하고, 대상을 분류하고, 생명과 구조를 더 높은 형식으로 배치하려 한다. 살아내려는 장력은 균형계로 굳었다. 이 장력은 이름과 사회, 몸과 신앙, 국가와 생활의 반복을 통해 세계를 계속 살게 만든다. 해체하려는 장력은 파괴계로 굳었다. 이 장력은 죽음, 붕괴, 공허, 포식과 생존전쟁을 통해 굳은 구조를 풀어내려 한다.\n\n옛 세계의 잎, 줄기, 뿌리도 이 봉합에 재사용되었다. 잎세계의 흔적은 창조계 페라파논의 그릇이 되었고, 줄기세계의 흔적은 균형계 코르모스의 그릇이 되었으며, 뿌리세계의 흔적은 파괴계 타르타리자의 그릇이 되었다. 그래서 세 세계는 새로 그은 도식보다 오래된 세계의 잔해와 오리진의 상처가 겹친 응급 구조다.\n\n이 우주에서 꼬임은 결함을 넘어 생명, 딜레마, 군상이라는 형식을 만든다. 서로 다른 힘이 한 방향으로 풀리는 대신 얽혀 있을 때 살아 있는 구조가 생긴다. 장력이 모두 풀리면 세계는 풀림으로 사라지고, 한 방향으로 과도하게 당겨지면 끊김이 발생한다. 살아 있는 존재와 사회는 그 사이에서 꼬임을 유지하며, 삼위의 군상이라는 형식은 이 꼬임을 여러 인물의 선택과 책임으로 보여 주는 방식이다.",
  "metadata": {
    "char_count": 793,
    "sha256": "2748c4f704241afd0913fa294c22f03c63275a89ba186dee77f11431a2a5b27b"
  }
}