{
  "id": "doc_cf3c85a6624506df:001",
  "document_id": "doc_cf3c85a6624506df",
  "path": "wiki/characters/fellsions/모방의_펠시온/index.md",
  "wiki_path": "characters/fellsions/모방의_펠시온/index.md",
  "title": "모방의 펠시온",
  "section": "개요",
  "summary": "모방의 펠시온은 공허 출신의 학습형 약탈자이며, 만화경의 눈으로 강자의 움직임과 에너지 흐름을 분해해 기술을 자기 방식으로 재조합한다.",
  "status": "draft",
  "type": "character",
  "tags": [
    "reader",
    "인물",
    "character"
  ],
  "updated": "2026-06-28",
  "url": "https://crangprang.github.io/TRINITY_WIKI_AI_READER/ai/chunks/doc_cf3c85a6624506df_001.json",
  "text": "## 개요\n\n모방의 펠시온은 강자의 기술을 보고, 빼앗고, 분해하고, 자기 기술로 다시 조립하는 학습형 약탈자다. 파괴계 최약체인 공허 출신으로 태어나 힘의 총량 대신 관찰과 기술 체득으로 생존한다.\n\n모방은 일부러 과장되고 우스꽝스러운 광대 배우를 연기한다. 상대가 그를 얕보는 순간 경계심이 낮아지고, 전투의 밑바닥 기술부터 비장의 수까지 차례로 드러난다. 모방은 그 모든 움직임을 만화경의 눈에 담아 자신의 기술로 재탄생시킨다.",
  "metadata": {
    "char_count": 242,
    "sha256": "777770d8a1accae54689daeaa3688300f478ed67f6577a484f76ab97231d912c"
  }
}