{
  "id": "doc_cef1737a1a08b3c9:020",
  "document_id": "doc_cef1737a1a08b3c9",
  "path": "wiki/universe/realms/balance/nations/알렉시아.md",
  "wiki_path": "universe/realms/balance/nations/알렉시아.md",
  "title": "알렉시아",
  "section": "에키드나와 벌레",
  "summary": "알렉시아는 푸른 수정과 촛불이 밤을 버티는 질문의 지하 도시다.",
  "status": "draft",
  "type": "nation",
  "tags": [
    "reader",
    "국가",
    "nation"
  ],
  "updated": "2026-06-28",
  "url": "https://crangprang.github.io/TRINITY_WIKI_AI_READER/ai/chunks/doc_cef1737a1a08b3c9_020.json",
  "text": "### 에키드나와 벌레\n\n에키드나는 질문을 먹고 벌레와 거짓된 해답을 밀어 올리는 용이다. 벌레는 빛을 따라 증식하고, 인간의 생각과 서가의 문장, 정보 수정의 결을 갉아먹으며 오염을 남긴다. 니드호그는 대색인수의 뿌리 부식을 상징하는 연출로 남고, 알렉시아의 중심 용 압력은 에키드나가 잡는다.",
  "metadata": {
    "char_count": 165,
    "sha256": "bdfd84bfc5386aabebbd7473028c288428d65ec451d5efcb7ae581d3b4c83394"
  }
}