{
  "id": "doc_eb0326149ddeb791:003",
  "document_id": "doc_eb0326149ddeb791",
  "path": "wiki/events/world_history/3시대_재창조에서_아홉_나라의_시대까지.md",
  "wiki_path": "events/world_history/3시대_재창조에서_아홉_나라의_시대까지.md",
  "title": "세계사/3시대",
  "section": "아난케의 마지막 해체",
  "summary": "3시대는 칼시네이션 이후 삼위일체 우주 재창조, 지혜의 창조주 참칭, 감독의 타락, 혼돈의 시대, 대공명, 삼위정교, 스트레인저, 대붕괴까지 이어지는 아홉 나라 체제 성립의 시대다.",
  "status": "draft",
  "type": "event",
  "tags": [
    "events",
    "world-history",
    "era"
  ],
  "updated": "2026-06-30",
  "url": "https://crangprang.github.io/TRINITY_WIKI_AI_READER/ai/chunks/doc_eb0326149ddeb791_003.json",
  "text": "## 아난케의 마지막 해체\n\n칼시네이션 뒤 세계는 다시 끊김 직전에 놓인다. 아난케는 에마나치온과 칼시네이션을 지나며 한 가지 가능성을 본다. 완전한 계획도, 전능한 개입도, 영웅적 이상도 세계를 살리지 못했다. 마지막 순간 세계를 붙잡은 것은 서로를 붙들고 다음 순간을 살려는 작은 생명의 의지였다.\n\n작은 생명의 의지는 멸망의 순간에도 곁의 사람을 놓지 않으려는 마찰, 다음 호흡을 잇고 싶다는 본능, 이미 사라진 다중우주에서 흘러든 티끌 같은 반발력이 섭리 안에서 드러난 힘이다. 아난케는 두 번의 멸망 뒤에야 이 힘을 확신하고, 피조물이 스스로 장력을 붙들 가능성을 마지막 선택지로 받아들인다.\n\n아난케는 그 의지에 마지막 가능성을 건다. 남은 인격과 의지, 신성과 위상까지 해체해 마지막 신비 섬유로 물레에 건다. 해체된 창조주의 섬유는 우주 안에 퍼지고, 이후 창조주의 목소리로 들리는 명령은 라케시스가 씌운 이름과 조작된 기록에서 생긴다.\n\n불지피기 의식에서 잠시 결합했다가 흩어진 오리진 조각은 힘을 아홉 보물에 남긴다. 그 힘은 다시 아홉 보물 안으로 프랙털처럼 퍼지고, 힘이 빠진 오리진 조각의 껍데기는 세 세계의 중력원과 지반 핵이 된다. 이때 잎세계는 창조계 페라파논으로, 줄기세계는 균형계 코르모스로, 뿌리세계는 파괴계 타르타리자로 굳는다.\n\n아홉 보물 안에 남아 있던 영웅들의 고결한 의지와 긍정 이데아는 트리네아드로 승화한다. 보물 자체는 핵심 영혼을 잃은 빈 위상그릇이 되고, 아홉 용의 정수는 자연 속으로 밀려난다. 이 분리에서 트리네아드, 보물 계승, 엑시온, 아포라투스, 페르소나의 기원이 갈라진다.",
  "metadata": {
    "char_count": 802,
    "sha256": "9706b73d998054be57f577061b2c84b2ef8171919188e68a14962a75c91f3351"
  }
}