{
  "id": "doc_fae9b6a12ec29dda:012",
  "document_id": "doc_fae9b6a12ec29dda",
  "path": "wiki/characters/main_party/세레나/index.md",
  "wiki_path": "characters/main_party/세레나/index.md",
  "title": "세레나",
  "section": "무덤을 찾는 망령",
  "summary": "세레나는 푸른 달 부족의 마지막 생존자이자 마지막 증언자다. 낡은 전사의 말투와 꼿꼿한 자세는 야수화와 동족 포식의 기억을 눌러 두는 갑옷이며, 검 너머에 남은 푸른 달의 이야기는 그녀가 아직 내려놓지 못한 삶의 형태다.",
  "status": "draft",
  "type": "character",
  "tags": [
    "reader",
    "인물",
    "character"
  ],
  "updated": "2026-06-28",
  "url": "https://crangprang.github.io/TRINITY_WIKI_AI_READER/ai/chunks/doc_fae9b6a12ec29dda_012.json",
  "text": "### 무덤을 찾는 망령\n\n`무덤을 찾는 망령`은 살아남은 죄책감과 자격 없음이 세레나를 다시 전장으로 밀어 넣는 층위다. 그녀는 아직도 투쟁의 나라 언어를 자기 말로 쓰지만, 그 말을 할 자격이 자신에게 있는지 끝내 확신하지 못한다.",
  "metadata": {
    "char_count": 131,
    "sha256": "3e2eb9761853fadbb39fd8da623d094398ed432a6df31ee8a730aa6d82f3c9c5"
  }
}