{
  "id": "doc_eb0326149ddeb791:015",
  "document_id": "doc_eb0326149ddeb791",
  "path": "wiki/events/world_history/3시대_재창조에서_아홉_나라의_시대까지.md",
  "wiki_path": "events/world_history/3시대_재창조에서_아홉_나라의_시대까지.md",
  "title": "세계사/3시대",
  "section": "퍼시스 사건",
  "summary": "3시대는 칼시네이션 이후 삼위일체 우주 재창조, 지혜의 창조주 참칭, 감독의 타락, 혼돈의 시대, 대공명, 삼위정교, 스트레인저, 대붕괴까지 이어지는 아홉 나라 체제 성립의 시대다.",
  "status": "draft",
  "type": "event",
  "tags": [
    "events",
    "world-history",
    "era"
  ],
  "updated": "2026-06-30",
  "url": "https://crangprang.github.io/TRINITY_WIKI_AI_READER/ai/chunks/doc_eb0326149ddeb791_015.json",
  "text": "## 퍼시스 사건\n\n퍼시스는 대공명 때 시트리노와 함께 균열을 봉합하러 다녔던 저주받은 자다. 그는 사람들을 구하기 위해 희생한 동료들이 기록도 보상도 없이 사라지는 현실을 보았다. 그가 처음 요구한 것은 죽은 이들의 이름과 저주받은 자들이 실제로 했던 일을 기록하고 인정해 달라는 호소였다. 삼위정교가 저주받은 자를 관리해야 할 적으로 재분류하면서, 퍼시스의 실망은 체제 정당성에 대한 분노로 바뀐다.\n\n퍼시스는 공의회와 정교가 자기 권위를 세우는 방식까지 겨눈다. 첫 올림피아 제전은 그에게 가장 상징적인 무대였다. 공의회, 정교, 빈 공좌, 교리 낭독, 체제 서약이 한꺼번에 공인되는 순간이기 때문이다.\n\n퍼시스의 요구는 보상 문제가 아니었다. 죽은 자들의 이름과 저주받은 자들의 공로가 공식 기록에 오르는 순간, 대공명의 진짜 희생과 방금 세워진 정교의 조작된 질서가 같은 문서 위에서 충돌하게 된다. 라케시스에게 그것은 한 사람의 반란보다, 막 만들어 둔 거짓말이 들키는 또 다른 대공명이자 실패로 읽혔다.\n\n라케시스는 아조트로 퍼시스를 직접 죽이고 기억을 편집한다. 공적 기록은 초대 투쟁의 엑시온이 퍼시스와 동귀어진했다고 말하고, 그 서사는 라케시스의 살해와 조작을 덮는다. 퍼시스는 고요한 종말의 사도라는 낙인을 쓰고, 저주받은 자들은 이레귤러로 호명된다. 진실을 지키기 위해 시작한 거짓말은, 그 거짓말을 지키기 위한 더 큰 거짓말로 자란다.\n\n시트리노의 죄는 다른 형태로 남는다. 그는 퍼시스를 한동안 도왔지만, 퍼시스가 죽은 자들의 이름과 봉합의 기록을 인정받기 위해 결정적 도움을 청했을 때 물러났다. 자신의 과거, 리그레드를 닮은 퍼시스, 다시 파국을 부를지 모른다는 두려움, 그리고 더 큰 계획이 그를 붙잡았다. 이 외면은 아조트 속 오피온의 부름을 외면했던 과거와 같은 결을 이룬다. 퍼시스가 죽은 뒤 시트리노는 또 한 번 크게 후회한다.",
  "metadata": {
    "char_count": 932,
    "sha256": "9149cba2480a687b395565ecce573e342b8feb66ce59ed3ba337ac3639be9539"
  }
}