{
  "id": "doc_663c7c05554a0840:005",
  "document_id": "doc_663c7c05554a0840",
  "path": "wiki/characters/axions/프로스페로/support/appearance.md",
  "wiki_path": "characters/axions/프로스페로/support/appearance.md",
  "title": "프로스페로 외형",
  "section": "시각 경계",
  "summary": "프로스페로의 40대 선장 실루엣, 긴 코트와 큰 모자, 찢어진 돛과 선장 해골표식이 합쳐진 전면 가면, 항로 소품을 다루는 외형 항목.",
  "status": "draft",
  "type": "character_support",
  "tags": [
    "reader",
    "character",
    "support",
    "appearance"
  ],
  "updated": "2026-06-26",
  "url": "https://crangprang.github.io/TRINITY_WIKI_AI_READER/ai/chunks/doc_663c7c05554a0840_005.json",
  "text": "## 시각 경계\n\n- 두루마리와 계약서는 중심 소품에서 벗어난다.\n- 해적 마크의 단순 부착은 프로스페로의 찢어진 돛 가면을 약하게 만든다.\n- 군복 장식이 강해지면 방주 선장과 구조대 지휘자의 인상이 흐려진다.",
  "metadata": {
    "char_count": 118,
    "sha256": "160aea6f64af2db2815563d1e02f94e3fd9f471f95c56ae9021d08670abd71e6"
  }
}