{
  "id": "doc_ebce86f03c6cf436:000",
  "document_id": "doc_ebce86f03c6cf436",
  "path": "wiki/characters/axions/유리디스_도리안_드_발루아/index.md",
  "wiki_path": "characters/axions/유리디스_도리안_드_발루아/index.md",
  "title": "유리디스 도리안 드 발루아",
  "section": "유리디스 도리안 드 발루아",
  "summary": "유리디스 도리안 드 발루아는 우니오네의 엑시온이자 스푸마토 왕실의 여왕으로, 꿈의 독성을 알면서도 침몰하는 현실을 견딜 만한 아름다운 장면으로 연출한다.",
  "status": "draft",
  "type": "character",
  "tags": [
    "reader",
    "인물",
    "character"
  ],
  "updated": "2026-06-28",
  "url": "https://crangprang.github.io/TRINITY_WIKI_AI_READER/ai/chunks/doc_ebce86f03c6cf436_000.json",
  "text": "# 유리디스 도리안 드 발루아\n\n| 항목 | 내용 |\n|---|---|\n| 분류 | 인물 |\n| 이름 | 유리디스 도리안 드 발루아 |\n| 성별/프레젠테이션 | 여성 |\n| 머리색 | 금색 |\n| 눈색 | 녹색 |\n| 소속/지역 | 9성좌 공의회, 예술의 나라 [우니오네](../../../universe/realms/balance/nations/우니오네.md), 스푸마토 왕실 |\n| 직책/역할 | 여왕, 엑시온, 예술 성좌 |\n| 계승 상태 | 계승자 엑시온 |\n| 연결된 아포라투스 | 미메시스 |\n| 제어기관 | 마고리아 |\n| 보물 | 꿈의 보물, 사이프러스 단검 |\n| 권능 | 물, 수면, 꿈의 문, 감정의 연출 |\n| 보물 선택 조건 | 꿈의 독성을 알면서도 침몰하는 현실을 견딜 만한 장면으로 꾸미려는 외면과 상실 |\n| 왕권 상징 | 사이프러스 단검, 데칼코마니 무도회 가면, 붉은 수면과 젖은 초대장 |\n| 대응 페르소나 | [빈센트](../../personas/빈센트/index.md) |\n| 관련 인물 | [엘리자베스](../../main_party/엘리자베스/index.md) |",
  "metadata": {
    "char_count": 562,
    "sha256": "719bfdddf6700e85e63de2b67465779a12f24c6604325c687d8154bece529004"
  }
}