{
  "id": "doc_efc482071b704108:000",
  "document_id": "doc_efc482071b704108",
  "path": "wiki/events/삼위의_군상/2부/신들의_시대/줄거리.md",
  "wiki_path": "events/삼위의_군상/2부/신들의_시대/줄거리.md",
  "title": "삼위의 군상/2부/신들의 시대/줄거리",
  "section": "삼위의 군상/2부/신들의 시대/줄거리",
  "summary": "아홉 나라의 시대 이후 열린 삼계 무대에서, 신격과 계승자들이 오리진의 완성을 두고 충돌하는 2부의 큰 줄거리다.",
  "status": "draft",
  "type": "story",
  "tags": [
    "story",
    "narrative",
    "삼위의_군상",
    "신들의_시대"
  ],
  "updated": "2026-06-29",
  "url": "https://crangprang.github.io/TRINITY_WIKI_AI_READER/ai/chunks/doc_efc482071b704108_000.json",
  "text": "# 삼위의 군상/2부/신들의 시대/줄거리\n\n| 항목 | 내용 |\n|---|---|\n| 작품 구간 | 삼위의 군상 2부 |\n| 시대명 | 신들의 시대 |\n| 서술 범위 | 1부 이후의 세계 상태, 두 번째 불지피기, 오리진 완성 직전까지의 거대 줄기 |\n| 상세도 | 대강의 큰 줄거리. 에피소드 단위 전개와 관계도는 별도 지시 전까지 확정하지 않는다. |",
  "metadata": {
    "char_count": 198,
    "sha256": "fd6c10be4115f2063c2c4fc3f7817cb6c0f1f41c1cc259d39e18eac971c96418"
  }
}