{
  "id": "doc_663c7c05554a0840:001",
  "document_id": "doc_663c7c05554a0840",
  "path": "wiki/characters/axions/프로스페로/support/appearance.md",
  "wiki_path": "characters/axions/프로스페로/support/appearance.md",
  "title": "프로스페로 외형",
  "section": "외형 기준",
  "summary": "프로스페로의 40대 선장 실루엣, 긴 코트와 큰 모자, 찢어진 돛과 선장 해골표식이 합쳐진 전면 가면, 항로 소품을 다루는 외형 항목.",
  "status": "draft",
  "type": "character_support",
  "tags": [
    "reader",
    "character",
    "support",
    "appearance"
  ],
  "updated": "2026-06-26",
  "url": "https://crangprang.github.io/TRINITY_WIKI_AI_READER/ai/chunks/doc_663c7c05554a0840_001.json",
  "text": "## 외형 기준\n\n| 항목 | 기준 |\n|---|---|\n| 성별/프레젠테이션 | 남성 |\n| 나이 | 40대, 콧수염과 선장 모자가 어울리는 인상 |\n| 실루엣 | 긴 코트와 큰 모자, 복수와 구출을 짊어진 방주 선장 |\n| 의상 | 방주 선장, 구조대 지휘자, 구름 항로의 현장 책임자 |\n| 가면 | 찢어진 돛과 오래된 선장 해골표식이 합쳐진 전면 가면 |\n| 소품 | 조타륜, 나침반, 밧줄, 항로 지도, 편지 봉인 |\n| 배경 | 비행 방주 갑판, 돛, 밧줄, 구름 항로 |\n| 표정/자세 | 항로를 통제하는 선장성, 구조와 추격을 함께 짊어진 지휘 자세 |",
  "metadata": {
    "char_count": 317,
    "sha256": "46a4ef90cf478b2a54fb0e6a59257b49cb08370ed9ac5694377b8ddeedf3cfb5"
  }
}