{
  "id": "doc_d916d1997fb02d74:025",
  "document_id": "doc_d916d1997fb02d74",
  "path": "wiki/characters/trineads/감독/index.md",
  "wiki_path": "characters/trineads/감독/index.md",
  "title": "감독",
  "section": "자연의 트리네아드와 생명의 트리네아드",
  "summary": "감독은 창조계의 총책임자이자 균형계를 거대한 비극 무대로 재설계한 연출가다. 그녀는 창조주로 믿은 지혜에게 도구처럼 소모되었다는 배신감 속에서 구원, 희망, 사랑, 미래를 거짓으로 판정하고, 파국 앞에서 폭발하는 순간의 감정만을 현실의 진실로 여긴다.",
  "status": "draft",
  "type": "character",
  "tags": [
    "reader",
    "인물",
    "character"
  ],
  "updated": "2026-06-29",
  "url": "https://crangprang.github.io/TRINITY_WIKI_AI_READER/ai/chunks/doc_d916d1997fb02d74_025.json",
  "text": "### 자연의 트리네아드와 생명의 트리네아드\n\n자연의 트리네아드와 생명의 트리네아드는 감독의 가족이자 정서적 앵커다. 두 자매는 감독의 광기와 나약함을 전부 알지는 못하지만, 그녀가 겉모습과 속모습 사이에서 흔들릴 때도 곁에 남는다. 감독에게 두 자매는 완전히 무너지지 않게 붙잡는 마지막 현실이다.\n\n두 자매는 감독의 설계에 자발적으로 가담한 공모자다. 자연은 이번 우주가 마지막 우주라는 사실을 마주한 뒤, 모든 것이 다시 순환하는 우주를 꿈꾸며 감독 곁에 선다. 생명은 용과 신의 시대를 넘어 다음 단계의 생명을 보고 싶어 하는 욕망 때문에 감독 곁에 선다. 이 자발성 때문에 감독의 창조계는 한 사람의 광기보다 넓은 공모 구조가 된다.",
  "metadata": {
    "char_count": 359,
    "sha256": "8e0b28bdbd08f3142c7fd04c56309c6fd225f915fc2f9d5fb922d393780ea1a5"
  }
}